MANIFEST.in
README.rst
setup.py
tesouro/__init__.py
tesouro/dates.py
tesouro/holidays.csv
tesouro/direto/__init__.py
tesouro/direto/calculator.py
tesouro/direto/client.py
tesouro/direto/importer.py
tesouro/direto/reporter.py
tesouro/templates/brokerage.html
tesouro/templates/email.html
tesouro_direto.egg-info/PKG-INFO
tesouro_direto.egg-info/SOURCES.txt
tesouro_direto.egg-info/dependency_links.txt
tesouro_direto.egg-info/requires.txt
tesouro_direto.egg-info/top_level.txt