Metadata-Version: 1.1
Name: tesouro-direto
Version: 0.1.0
Summary: Tools to manage 'Tesouro Direto' information.
Home-page: http://github.com/vkruoso/tesouro-direto
Author: Vinicius K. Ruoso
Author-email: vinicius.ruoso@gmail.com
License: MIT License
Platform: any
Classifier: Programming Language :: Python
Classifier: Development Status :: 4 - Beta
Classifier: Natural Language :: English
Classifier: Intended Audience :: Developers
Classifier: Intended Audience :: End Users/Desktop
Classifier: Intended Audience :: Financial and Insurance Industry
Classifier: License :: OSI Approved :: MIT License
Classifier: Operating System :: OS Independent
Classifier: Topic :: Utilities
Classifier: Topic :: Office/Business :: Financial :: Investment
Classifier: Topic :: Software Development :: Libraries :: Python Modules
